<?xml version="1.0" encoding="ISO-8859-1"?>
<archives descrAccount="una città per gli archivi" idAccount="CPA">
	<archGroup name="Fondi in corso di inventariazione: storico">
		<arch db="cpaSt07" host="asclepio" port="-1" user="lettore" password="" pne="c">Associazione tra i familiari delle vittime della strage alla stazione di Bologna del 2 agosto 1980</arch>
		<arch db="cpaSt15" host="asclepio" port="-1" user="lettore" password="" pne="c">Accademia Nazionale di Agricoltura</arch>
		<arch db="cpaSt08" host="asclepio" port="-1" user="lettore" password="" pne="c">Accademia Nazionale di belle arti di Bologna già Accademia Clementina</arch>
		<arch db="cpaSt10" host="asclepio" port="-1" user="lettore" password="" pne="c">Antoniano dei frati minori della provincia minoritica di Cristo Re</arch>
		<arch db="cpaSt27" host="asclepio" port="-1" user="lettore" password="" pne="c">Associazione Nazionale Partigiani d'Italia</arch>
		<arch db="cpaSt34" host="asclepio" port="-1" user="lettore" password="" pne="c">Associazione costituzionale delle Romagne</arch>
		<arch db="cpaSt49" host="asclepio" port="-1" user="lettore" password="" pne="c">Associazione Orlando</arch>
		<arch db="cpaSt38" host="asclepio" port="-1" user="lettore" password="" pne="c">Archivio Pepoli</arch>
		<arch db="cpaSt48" host="asclepio" port="-1" user="lettore" password="" pne="c">Azienda casa Emilia Romagna della Provincia di Bologna (ACER ex IACP)</arch>
		<arch db="cpaSt44" host="asclepio" port="-1" user="lettore" password="" pne="c">Azienda pubblica di servizio (APS) Giovanni XXIII</arch>
		<arch db="cpaSt39" host="asclepio" port="-1" user="lettore" password="" pne="c">Azienda unità sanitaria locale</arch>
		<arch db="cpaSt30" host="asclepio" port="-1" user="lettore" password="" pne="c">Banca del Monte di Bologna</arch>
		<arch db="cpaSt51" host="asclepio" port="-1" user="lettore" password="" pne="c">Carlo Musi</arch>
		<arch db="cpaSt14" host="asclepio" port="-1" user="lettore" password="" pne="c">Casa Lyda Borelli per artisti e operatori dello spettacolo</arch>
		<arch db="cpaSt13" host="asclepio" port="-1" user="lettore" password="" pne="c">CGIL regionale Emilia-Romagna</arch>
		<arch db="cpaSt20" host="asclepio" port="-1" user="lettore" password="" pne="c">CISL - Unione sindacale territoriale Bologna</arch>
		<arch db="cpaSt52" host="asclepio" port="-1" user="lettore" password="" pne="c">Commediografi Bolognesi</arch>
		<arch db="cpaSt37" host="asclepio" port="-1" user="lettore" password="" pne="c">Comune di Bologna / Mappe e piante</arch>
		<arch db="cpaSt05" host="asclepio" port="-1" user="lettore" password="" pne="c">Comune di Bologna / Scuole tecniche bolognesi istituti Aldini Valeriani e Sirani</arch>
		<arch db="cpaSt09" host="asclepio" port="-1" user="lettore" password="" pne="c">Comune di Bologna / Segreteria generale</arch>
		<arch db="cpaSt01" host="asclepio" port="-1" user="lettore" password="" pne="c">Comune di Bologna / Unità intermedia studi e interventi storico-monumentali</arch>
		<arch db="cpaSt32" host="asclepio" port="-1" user="lettore" password="" pne="c">Consorzio della bonifica Reno-Palata</arch>
		<arch db="cpaSt25" host="asclepio" port="-1" user="lettore" password="" pne="c">Ente provinciale per il turismo</arch>
		<arch db="cpaSt31" host="asclepio" port="-1" user="lettore" password="" pne="c">Famiglia Comelli</arch>
		<arch db="cpaSt22" host="asclepio" port="-1" user="lettore" password="" pne="c">Famèja Bulgnèisa</arch>
		<arch db="cpaSt29" host="asclepio" port="-1" user="lettore" password="" pne="c">Federico Parasini</arch>
		<arch db="cpaSt43" host="asclepio" port="-1" user="lettore" password="" pne="c">Fondazione Archivio Guidotti Magnani</arch>
		<arch db="cpaSt21" host="asclepio" port="-1" user="lettore" password="" pne="c">Fondo Ferlini</arch>
		<arch db="cpaSt35" host="asclepio" port="-1" user="lettore" password="" pne="c">Gabinetto della Prefettura (Archivio riservato)</arch>
		<arch db="cpaSt42" host="asclepio" port="-1" user="lettore" password="" pne="c">Gabinetto della Questura, categoria A8 (Persone Pericolose per la Sicurezza dello Stato)</arch>
		<arch db="cpaSt03" host="asclepio" port="-1" user="lettore" password="" pne="c">Giuseppe Ceneri</arch>
		<arch db="cpaSt41" host="asclepio" port="-1" user="lettore" password="" pne="c">Giuseppe Pepoli</arch>
		<arch db="cpaSt06" host="asclepio" port="-1" user="lettore" password="" pne="c">Guardia nazionale di Bologna</arch>
		<arch db="cpaSt64" host="asclepio" port="-1" user="lettore" password="" pne="c">ISREBO</arch>
		<arch db="cpaSt45" host="asclepio" port="-1" user="lettore" password="" pne="c">Istituti ortopedici Rizzoli (inventario Sesamo)</arch>
		<arch db="cpaSt33" host="asclepio" port="-1" user="lettore" password="" pne="c">Istituto Comprensivo 3 "Lame" (Scuola Elementare e Media Bottego e Scuola Elementare e Media S. d'Acquisto)</arch>
		<arch db="cpaSt24" host="asclepio" port="-1" user="lettore" password="" pne="c">Istituto scolastico Pier Crescenzi-Pacinotti</arch>
		<arch db="cpaSt50" host="asclepio" port="-1" user="lettore" password="" pne="c">Istituto scolastico Pier Crescenzi-Pacinotti (inventario Sesamo)</arch>
		<arch db="cpaSt11" host="asclepio" port="-1" user="lettore" password="" pne="c">Jakob Moleschott</arch>
		<arch db="cpaSt66" host="asclepio" port="-1" user="lettore" password="" pne="c">Jean Louis Protche - nuova struttura (microschede)</arch>
		<arch db="cpaSt36" host="asclepio" port="-1" user="lettore" password="" pne="c">Liceo Ginnasio Statale Luigi Galvani</arch>
		<arch db="cpaSt26" host="asclepio" port="-1" user="lettore" password="" pne="c">Liceo scientifico Augusto Righi</arch>
		<arch db="cpaSt40" host="asclepio" port="-1" user="lettore" password="" pne="c">Marco Minghetti</arch>
		<arch db="cpaSt47" host="asclepio" port="-1" user="lettore" password="" pne="c">OMNI</arch>
		<arch db="cpaSt17" host="asclepio" port="-1" user="lettore" password="" pne="c">Oreste Regnoli</arch>
		<arch db="cpaSt02" host="asclepio" port="-1" user="lettore" password="" pne="c">Partito comunista italiano - Federazione di Bologna</arch>
		<arch db="cpaSt46" host="asclepio" port="-1" user="lettore" password="" pne="c">Archivio storico della Provincia di Cristo Re dei frati minori dell'Emilia Romagna (convertito da Word - maggio 2010)</arch>
		<arch db="cpaSt18" host="asclepio" port="-1" user="lettore" password="" pne="c">Quirico Filopanti</arch>
		<arch db="cpaSt19" host="asclepio" port="-1" user="lettore" password="" pne="c">Raccolta Suppini</arch>
		<arch db="cpaSt12" host="asclepio" port="-1" user="lettore" password="" pne="c">Raffaele Spongano</arch>
		<arch db="cpaSt16" host="asclepio" port="-1" user="lettore" password="" pne="c">Regia accademia filarmonica di Bologna</arch>
		<arch db="cpaSt23" host="asclepio" port="-1" user="lettore" password="" pne="c">Salsamentari</arch>
		<arch db="cpaSt53" host="asclepio" port="-1" user="lettore" password="" pne="c">Sebastiano Sani</arch>
		<arch db="cpaSt28" host="asclepio" port="-1" user="lettore" password="" pne="c">Società artigiana</arch>
		<arch db="cpaSt54" host="asclepio" port="-1" user="lettore" password="" pne="c">Fondo famiglia Pascale</arch>
		<arch db="cpaSt55" host="asclepio" port="-1" user="lettore" password="" pne="c">Fondo famiglia Senni</arch>
		<arch db="cpaSt56" host="asclepio" port="-1" user="lettore" password="" pne="c">Fondo Bianconi</arch>
		<arch db="cpaSt57" host="asclepio" port="-1" user="lettore" password="" pne="c">Fondo Boriani</arch>
		<arch db="cpaSt58" host="asclepio" port="-1" user="lettore" password="" pne="c">Fondo Raule</arch>
		<arch db="cpaSt59" host="asclepio" port="-1" user="lettore" password="" pne="c">Fondo Marcovigi</arch>
		<arch db="cpaSt60" host="asclepio" port="-1" user="lettore" password="" pne="c">Fondo Maragi</arch>
		<arch db="cpaSt61" host="asclepio" port="-1" user="lettore" password="" pne="c">Fondo Mattioli</arch>
		<arch db="cpaSt62" host="asclepio" port="-1" user="lettore" password="" pne="c">Fondo Marchetti</arch>
		<arch db="cpaSt63" host="asclepio" port="-1" user="lettore" password="" pne="c">Fondo Masseangelo Masseangeli</arch>
		<arch db="cpaSt65" host="asclepio" port="-1" user="lettore" password="" pne="c">Archivio provinciale dei cappuccini di Bologna</arch>
		<arch db="cpaSt67" host="asclepio" port="-1" user="lettore" password="" pne="c">Fondo Piero Bertolini</arch>
		<arch db="cpaSt68" host="asclepio" port="-1" user="lettore" password="" pne="c">Fondo Parisini</arch>
		<arch db="cpaSt69" host="asclepio" port="-1" user="lettore" password="" pne="c">Associazione parenti delle vittime della strage di Ustica</arch>
		<arch db="cpaSt70" host="asclepio" port="-1" user="lettore" password="" pne="c">Istituto Parri</arch>
		<arch db="cpaSt71" host="asclepio" port="-1" user="lettore" password="" pne="c">Fondazione Guglielmo Marconi</arch>
		<arch db="cpaSt72" host="asclepio" port="-1" user="lettore" password="" pne="c">Pci Federazione di Bologna. Triumvirato Insurrezionale 1943-1945</arch>
		<arch db="cpaSt73" host="asclepio" port="-1" user="lettore" password="" pne="c">Biblioteca del Dipartimento di Italianistica - Università degli studi di Bologna</arch>
		<arch db="cpaSt74" host="asclepio" port="-1" user="lettore" password="" pne="c">Giovanna Grignaffini</arch>
		<arch db="cpaSt75" host="asclepio" port="-1" user="lettore" password="" pne="c">Anna Laura Mariani</arch>
	</archGroup>
	<archGroup name="Fondi in corso di inventariazione: fotografico">
		<arch db="cpaFt02" host="asclepio" port="-1" user="lettore" password="" pne="c">Antoniano dei frati minori della provincia minoritica di Cristo Re - fotografico</arch>
		<arch db="cpaFt05" host="asclepio" port="-1" user="lettore" password="" pne="c">Associazione Unione Fotografi Organizzati</arch>
		<arch db="cpaFt08" host="asclepio" port="-1" user="lettore" password="" pne="c">Associazione nazionale partigiani d'Italia - fotografico</arch>
		<arch db="cpaFt13" host="asclepio" port="-1" user="lettore" password="" pne="c">Azienda unità sanitaria locale - fotografico</arch>
		<arch db="cpaFt15" host="asclepio" port="-1" user="lettore" password="" pne="c">Museo di Ronzano / Libertà Carducci - fotografico</arch>
		<arch db="cpaFt16" host="asclepio" port="-1" user="lettore" password="" pne="c">Comune di Bologna / Unità intermedia studi e interventi storico-monumentali - fotografico</arch>
		<arch db="cpaFt17" host="asclepio" port="-1" user="lettore" password="" pne="c">Fondo Villani</arch>
		<arch db="cpaFt03" host="asclepio" port="-1" user="lettore" password="" pne="c">Casa Lyda Borelli per artisti e operatori dello spettacolo - fotografico</arch>
		<arch db="cpaFt11" host="asclepio" port="-1" user="lettore" password="" pne="c">Fondo AMPELOS - fotografico</arch>
		<arch db="cpaFt04" host="asclepio" port="-1" user="lettore" password="" pne="c">CGIL regionale Emilia-Romagna - fotografico</arch>
		<arch db="cpaFt10" host="asclepio" port="-1" user="lettore" password="" pne="c">Consorzio della bonifica Renana - fotografico</arch>
		<arch db="cpaFt09" host="asclepio" port="-1" user="lettore" password="" pne="c">Famèja Bulgnèisa - fotografico</arch>
		<arch db="cpaFt18" host="asclepio" port="-1" user="lettore" password="" pne="c">Famiglia Comelli - fotografico</arch>
		<arch db="cpaFt14" host="asclepio" port="-1" user="lettore" password="" pne="c">Istituto Rizzoli - fotografico</arch>
		<arch db="cpaFt06" host="asclepio" port="-1" user="lettore" password="" pne="c">Luigi Arbizzani, raccolta fotografica</arch>
		<arch db="cpaFt12" host="asclepio" port="-1" user="lettore" password="" pne="c">Teatro delle Moline - fotografico</arch>
	</archGroup>
	<archGroup name="Fondi in corso di inventariazione: manifesti">
		<arch db="cpaMn01" host="asclepio" port="-1" user="lettore" password="" pne="c">Associazione nazionale partigiani d'Italia - manifesti</arch>
		<arch db="cpaMn02" host="asclepio" port="-1" user="lettore" password="" pne="c">Antoniano dei frati minori della provincia minoritica di Cristo Re - manifesti</arch>
	</archGroup>
	<archGroup name="Fondi in corso di inventariazione: audiovisivo">
		<arch db="cpaVideo03" host="asclepio" port="-1" user="lettore" password="" pne="c">Antoniano dei frati minori della provincia minoritica di Cristo Re - audiovisivo</arch>
		<arch db="cpaVideo01" host="asclepio" port="-1" user="lettore" password="" pne="c">Arte video dell`Associazione Bo-Art</arch>
		<arch db="cpaVideo05" host="asclepio" port="-1" user="lettore" password="" pne="c">Archivio Nazionale del Film di famiglia</arch>
		<arch db="cpaVideo06" host="asclepio" port="-1" user="lettore" password="" pne="c">Fondo AMPELOS - audiovisivo</arch>
		<arch db="cpaVideo04" host="asclepio" port="-1" user="lettore" password="" pne="c">CGIL regionale Emilia-Romagna - audiovisivo</arch>
		<arch db="cpaVideo07" host="asclepio" port="-1" user="lettore" password="" pne="c">Teatro delle Moline - audiovisivo</arch>
	</archGroup>
	<archGroup name="Fondi in corso di inventariazione: sonoro">
		<arch db="cpaSonoro01" host="asclepio" port="-1" user="lettore" password="" pne="c">Associazione Orlando</arch>
	</archGroup>
	<archGroup name="Authority">
		<arch db="cpaAutherSPResp" host="asclepio" port="-1" user="lettore" password="" pne="eac-cpf">Authority Soggetti produttori e Responsabilità autoriali</arch>
		<arch db="cpaAutherEnti" host="asclepio" port="-1" user="lettore" password="" pne="eac">Authority Enti e Istituzioni</arch>
		<arch db="cpaAutherLuoghi" host="asclepio" port="-1" user="lettore" password="" pne="eac">Authority Luoghi</arch>
		<arch db="cpaAutherNomi" host="asclepio" port="-1" user="lettore" password="" pne="eac">Authority Persone</arch>
		<arch db="cpaAutherTemi" host="asclepio" port="-1" user="lettore" password="" pne="eac">Authority Temi</arch>
	</archGroup>
</archives>